pyaavso/__init__.py
pyaavso/utils.py
pyaavso/formats/__init__.py
pyaavso/formats/visual.py
pyaavso/parsers/__init__.py
pyaavso/parsers/webobs.py
pyaavso-0.2.dist-info/DESCRIPTION.rst
pyaavso-0.2.dist-info/METADATA
pyaavso-0.2.dist-info/RECORD
pyaavso-0.2.dist-info/WHEEL
pyaavso-0.2.dist-info/metadata.json
pyaavso-0.2.dist-info/top_level.txt
tests/formats/__init__.py
tests/formats/test_visual.py
tests/formats/visual.py
tests/parsers/__init__.py
tests/parsers/test_webobs.py
tests/parsers/webobs.py
