Metadata-Version: 2.0
Name: pyaavso
Version: 0.2
Summary: A Python library for working with AAVSO data.
Home-page: http://github.com/zsiciarz/pyaavso
Author: Zbigniew Siciarz
Author-email: zbigniew@siciarz.net
License: MIT
Download-URL: http://pypi.python.org/pypi/pyaavso
Platform: any
Classifier: Development Status :: 5 - Production/Stable
Classifier: Intended Audience :: Developers
Classifier: Intended Audience :: Science/Research
Classifier: License :: OSI Approved :: MIT License
Classifier: Operating System :: OS Independent
Classifier: Programming Language :: Python
Classifier: Programming Language :: Python :: 3
Classifier: Programming Language :: Python :: 3 :: Only
Classifier: Programming Language :: Python :: 3.3
Classifier: Programming Language :: Python :: 3.4
Classifier: Programming Language :: Python :: 3.5
Classifier: Programming Language :: Python :: 3.6
Classifier: Topic :: Scientific/Engineering :: Astronomy
Classifier: Topic :: Utilities
Requires-Dist: lxml (>=2.0)
Requires-Dist: requests (>=1.0)
